masakari/__init__.py
masakari/config.py
masakari/context.py
masakari/coordination.py
masakari/exception.py
masakari/i18n.py
masakari/manager.py
masakari/policy.py
masakari/rpc.py
masakari/safe_utils.py
masakari/service.py
masakari/utils.py
masakari/version.py
masakari/api/__init__.py
masakari/api/api_version_request.py
masakari/api/auth.py
masakari/api/urlmap.py
masakari/api/utils.py
masakari/api/versioned_method.py
masakari/api/wsgi.py
masakari/api/openstack/__init__.py
masakari/api/openstack/common.py
masakari/api/openstack/extensions.py
masakari/api/openstack/wsgi.py
masakari/api/openstack/ha/__init__.py
masakari/api/openstack/ha/extension_info.py
masakari/api/openstack/ha/hosts.py
masakari/api/openstack/ha/notifications.py
masakari/api/openstack/ha/segments.py
masakari/api/openstack/ha/versions.py
masakari/api/openstack/ha/versionsV1.py
masakari/api/openstack/ha/vmoves.py
masakari/api/openstack/ha/schemas/__init__.py
masakari/api/openstack/ha/schemas/hosts.py
masakari/api/openstack/ha/schemas/notifications.py
masakari/api/openstack/ha/schemas/payload.py
masakari/api/openstack/ha/schemas/segments.py
masakari/api/openstack/ha/views/__init__.py
masakari/api/openstack/ha/views/hosts.py
masakari/api/openstack/ha/views/versions.py
masakari/api/validation/__init__.py
masakari/api/validation/parameter_types.py
masakari/api/validation/validators.py
masakari/cmd/__init__.py
masakari/cmd/api.py
masakari/cmd/engine.py
masakari/cmd/manage.py
masakari/cmd/status.py
masakari/common/__init__.py
masakari/common/config.py
masakari/compute/__init__.py
masakari/compute/nova.py
masakari/conf/__init__.py
masakari/conf/api.py
masakari/conf/base.py
masakari/conf/coordination.py
masakari/conf/database.py
masakari/conf/engine.py
masakari/conf/engine_driver.py
masakari/conf/exceptions.py
masakari/conf/nova.py
masakari/conf/opts.py
masakari/conf/osapi_v1.py
masakari/conf/paths.py
masakari/conf/service.py
masakari/conf/ssl.py
masakari/conf/wsgi.py
masakari/db/__init__.py
masakari/db/api.py
masakari-20.0.0.dist-info/AUTHORS
masakari-20.0.0.dist-info/LICENSE
masakari-20.0.0.dist-info/METADATA
masakari-20.0.0.dist-info/WHEEL
masakari-20.0.0.dist-info/entry_points.txt
masakari-20.0.0.dist-info/pbr.json
masakari-20.0.0.dist-info/top_level.txt
masakari-20.0.0.dist-info/RECORD
