Metadata-Version: 2.1
Name: masakari
Version: 20.0.0
Summary: Virtual Machine High Availability (VMHA) service for OpenStack
Home-page: https://docs.openstack.org/masakari/latest/
Author: OpenStack
Author-email: openstack-discuss@lists.openstack.org
Classifier: Development Status :: 5 - Production/Stable
Classifier: Environment :: OpenStack
Classifier: Intended Audience :: Information Technology
Classifier: Intended Audience :: System Administrators
Classifier: License :: OSI Approved :: Apache Software License
Classifier: Operating System :: POSIX :: Linux
Classifier: Programming Language :: Python
Classifier: Programming Language :: Python :: 3
Classifier: Programming Language :: Python :: 3.10
Classifier: Programming Language :: Python :: 3.11
Classifier: Programming Language :: Python :: 3.12
Classifier: Programming Language :: Python :: 3 :: Only
Classifier: Programming Language :: Python :: Implementation :: CPython
Requires-Python: >=3.10
License-File: LICENSE
License-File: AUTHORS
Requires-Dist: alembic >=1.8.0
Requires-Dist: jsonschema >=3.2.0
Requires-Dist: keystoneauth1 >=3.4.0
Requires-Dist: keystonemiddleware >=4.17.0
Requires-Dist: WebOb >=1.7.1
Requires-Dist: microversion-parse >=0.2.1
Requires-Dist: oslo.config >=5.2.0
Requires-Dist: oslo.context >=2.19.2
Requires-Dist: oslo.db >=4.44.0
Requires-Dist: oslo.messaging >=14.1.0
Requires-Dist: oslo.i18n >=3.15.3
Requires-Dist: oslo.log >=3.36.0
Requires-Dist: oslo.middleware >=3.31.0
Requires-Dist: oslo.policy >=4.5.0
Requires-Dist: oslo.service !=1.28.1,>=1.24.0
Requires-Dist: oslo.upgradecheck >=1.3.0
Requires-Dist: oslo.utils >=4.7.0
Requires-Dist: oslo.versionedobjects >=1.31.2
Requires-Dist: pbr !=2.1.0,>=2.0.0
Requires-Dist: python-novaclient >=9.1.0
Requires-Dist: stevedore >=1.20.0
Requires-Dist: SQLAlchemy >=1.4.0
Requires-Dist: SQLAlchemy-Utils >=0.33.10
Requires-Dist: taskflow >=2.16.0
Requires-Dist: tooz >=2.10.1
